rocs_mt/__init__.py
rocs_mt/rocs_mt.py
rocs_mt-2.0.0.dist-info/METADATA
rocs_mt-2.0.0.dist-info/WHEEL
rocs_mt-2.0.0.dist-info/top_level.txt
rocs_mt-2.0.0.dist-info/RECORD
