Metadata-Version: 2.4
Name: rocs_mt
Version: 2.0.0
Summary: RoCS-MT, a Robust Challenge Set for Machine Translation (MT) -- version 2
Author-email: Rachel Bawden and Benoît Sagot <rachel.bawden@inria.fr>
License: CC-BY-NC
Project-URL: Homepage, https://github.com/rbawden/RoCS-MT/
Requires-Python: >=3.9
Requires-Dist: requests>=2.0
Requires-Dist: datasets>=2.13.1
Requires-Dist: typing>=3.7.4.3
